MANIFEST.in
setup.cfg
setup.py
abstrackr/__init__.py
abstrackr/websetup.py
abstrackr.egg-info/PKG-INFO
abstrackr.egg-info/SOURCES.txt
abstrackr.egg-info/dependency_links.txt
abstrackr.egg-info/entry_points.txt
abstrackr.egg-info/not-zip-safe
abstrackr.egg-info/paster_plugins.txt
abstrackr.egg-info/requires.txt
abstrackr.egg-info/top_level.txt
abstrackr/config/__init__.py
abstrackr/config/environment.py
abstrackr/config/middleware.py
abstrackr/config/routing.py
abstrackr/controllers/__init__.py
abstrackr/controllers/account.py
abstrackr/controllers/controller_globals.py
abstrackr/controllers/error.py
abstrackr/controllers/review.py
abstrackr/controllers/static_pages.py
abstrackr/controllers/trackr.py
abstrackr/lib/__init__.py
abstrackr/lib/abstrackr_dataset.py
abstrackr/lib/app_globals.py
abstrackr/lib/auth.py
abstrackr/lib/base.py
abstrackr/lib/extract_from_sql.py
abstrackr/lib/generate_predictions.py
abstrackr/lib/helpers.py
abstrackr/lib/make_predictions.py
abstrackr/lib/make_predictions_sklearn.py
abstrackr/lib/pubmedpy.py
abstrackr/lib/sklearn_predictor.py
abstrackr/lib/tfidf2.py
abstrackr/lib/xml_to_sql.py
abstrackr/lib/xml_to_sqlite.py
abstrackr/model/__init__.py
abstrackr/model/auth.py
abstrackr/model/form.py
abstrackr/model/meta.py
abstrackr/public/.DS_Store
abstrackr/public/Robot-icon.png
abstrackr/public/abstrackr.png
abstrackr/public/abstrackr_logo.png
abstrackr/public/accept.png
abstrackr/public/add.png
abstrackr/public/admin.png
abstrackr/public/admin_sm.png
abstrackr/public/arrow_right.png
abstrackr/public/bg.png
abstrackr/public/bg_tags.gif
abstrackr/public/conflicts_sm.png
abstrackr/public/delete.png
abstrackr/public/delete_sm.png
abstrackr/public/edit.png
abstrackr/public/edit_sm.png
abstrackr/public/export.png
abstrackr/public/export_sm.png
abstrackr/public/exporting.html
abstrackr/public/favicon.ico
abstrackr/public/jqModal.css
abstrackr/public/jquery-ui-1.8.15.custom.css
abstrackr/public/loading.gif
abstrackr/public/maybe.png
abstrackr/public/maybe_sm.png
abstrackr/public/merge.png
abstrackr/public/merge_sm.png
abstrackr/public/pylons-logo.gif
abstrackr/public/reject.png
abstrackr/public/review_conflicts.png
abstrackr/public/right.png
abstrackr/public/stylesheet.css
abstrackr/public/thumbs_down.png
