Metadata-Version: 1.0
Name: abstrackr
Version: 0.3.0dev
Summary: Web-based Citation Screening Tool
Home-page: https://research.brown.edu/myresearch/Byron_Wallace
Author: Byron Wallace
Author-email: byron_wallace@brown.edu
License: UNKNOWN
Platform: UNKNOWN
